fahoorm/__init__.py
fahoorm/exceptions.py
fahoorm/orm.py
fahoorm/session.py
tests/__init__.py
tests/test_fahoorm.py
fahoorm-0.1.0.dist-info/LICENSE
fahoorm-0.1.0.dist-info/METADATA
fahoorm-0.1.0.dist-info/WHEEL
fahoorm-0.1.0.dist-info/top_level.txt
fahoorm-0.1.0.dist-info/RECORD
