Metadata-Version: 2.1
Name: fahoorm
Version: 0.1.0
Summary: A custom ORM framework for Python
Home-page: https://github.com/lhoussaine-HSSINI/fahoorm
Author: Lhoussaine HSSINI and  Fatma KARKACH
Author-email: bontop.2028@gmail.com
Classifier: Development Status :: 3 - Alpha
Classifier: Intended Audience :: Developers
Classifier: Topic :: Software Development :: Libraries :: Python Modules
Classifier: License :: OSI Approved :: MIT License
Classifier: Programming Language :: Python :: 3
Classifier: Programming Language :: Python :: 3.6
Classifier: Programming Language :: Python :: 3.7
Classifier: Programming Language :: Python :: 3.8
License-File: LICENSE
Requires-Dist: pymysql
Requires-Dist: psycopg2
Requires-Dist: pymongo
